README.md
setup.py
householdpower/__init__.py
householdpower/householdpower.py
householdpower.egg-info/PKG-INFO
householdpower.egg-info/SOURCES.txt
householdpower.egg-info/dependency_links.txt
householdpower.egg-info/top_level.txt
test/__init__.py
test/householdpower_test.py